FCSAppAccess/__init__.py
FCSAppAccess/app_access.py
FCSAppAccess/exceptions.py
FCSAppAccess/models/__init__.py
FCSAppAccess/models/device_code.py
FCSAppAccessSDK-1.0.2.dist-info/LICENSE
FCSAppAccessSDK-1.0.2.dist-info/METADATA
FCSAppAccessSDK-1.0.2.dist-info/WHEEL
FCSAppAccessSDK-1.0.2.dist-info/top_level.txt
FCSAppAccessSDK-1.0.2.dist-info/RECORD
