Metadata-Version: 2.1
Name: FCSAppAccessSDK
Version: 1.0.2
Summary: The SDK for accessing FangCloudServices with Application Access Credentials
Home-page: https://github.com/CPSuperstore/FangCloudServicesAppAccessSDK
Author: CPSuperstore
Author-email: cpsuperstoreinc@gmail.com
License: Apache License 2.0
Project-URL: Bug Tracker, https://github.com/CPSuperstore/FangCloudServicesAppAccessSDK/issues
Keywords: FANG,CLOUD,SERVICES,FCS,SDK,USER,MANAGEMENT,OAUTH2,SECURITY
Platform: UNKNOWN
Classifier: Development Status :: 4 - Beta
Classifier: Intended Audience :: Developers
Classifier: Topic :: Security
Classifier: License :: OSI Approved :: Apple Public Source License
Classifier: Programming Language :: Python :: 3
Classifier: Programming Language :: Python :: 3.4
Classifier: Programming Language :: Python :: 3.5
Classifier: Programming Language :: Python :: 3.6
Classifier: Natural Language :: English
License-File: LICENSE
Requires-Dist: requests
